{
    "annotations": {
        "list": []
    },
    "editable": true,
    "fiscalYearStartMonth": 0,
    "graphTooltip": 1,
    "links": [],
    "liveNow": true,
    "refresh": "5s",
    "schemaVersion": 39,
    "tags": [
        "citl",
        "overview",
        "aspnetcore",
        "performance"
    ],
    "templating": {
        "list": [
            {
                "current": {
                    "selected": true,
                    "text": "All",
                    "value": "$__all"
                },
                "datasource": {
                    "type": "prometheus",
                    "uid": "prometheus"
                },
                "definition": "label_values(citl_http_requests_total, tenant)",
                "hide": 0,
                "includeAll": true,
                "label": "Tenant",
                "multi": true,
                "name": "tenant",
                "options": [],
                "query": {
                    "query": "label_values(citl_http_requests_total, tenant)",
                    "refId": "StandardVariableQuery"
                },
                "refresh": 2,
                "regex": "",
                "skipUrlSync": false,
                "sort": 1,
                "type": "query"
            }
        ]
    },
    "time": {
        "from": "now-5m",
        "to": "now"
    },
    "timepicker": {},
    "timezone": "",
    "title": "CITL — Application Overview",
    "uid": "citl-overview",
    "version": 1,
    "panels": [
        {
            "collapsed": false,
            "gridPos": {
                "h": 1,
                "w": 24,
                "x": 0,
                "y": 0
            },
            "id": 100,
            "title": "📊 Request Overview",
            "type": "row"
        },
        {
            "datasource": {
                "type": "prometheus",
                "uid": "prometheus"
            },
            "fieldConfig": {
                "defaults": {
                    "unit": "reqps",
                    "thresholds": {
                        "mode": "absolute",
                        "steps": [
                            {
                                "color": "green",
                                "value": null
                            },
                            {
                                "color": "yellow",
                                "value": 50
                            },
                            {
                                "color": "red",
                                "value": 200
                            }
                        ]
                    }
                }
            },
            "gridPos": {
                "h": 4,
                "w": 4,
                "x": 0,
                "y": 1
            },
            "id": 1,
            "options": {
                "reduceOptions": {
                    "calcs": [
                        "lastNotNull"
                    ]
                },
                "colorMode": "background",
                "graphMode": "area"
            },
            "title": "Request Rate",
            "type": "stat",
            "targets": [
                {
                    "expr": "sum(rate(citl_http_requests_total{tenant=~\"$tenant\"}[1m]))",
                    "legendFormat": "req/s"
                }
            ]
        },
        {
            "datasource": {
                "type": "prometheus",
                "uid": "prometheus"
            },
            "fieldConfig": {
                "defaults": {
                    "unit": "reqps",
                    "thresholds": {
                        "mode": "absolute",
                        "steps": [
                            {
                                "color": "green",
                                "value": null
                            },
                            {
                                "color": "orange",
                                "value": 1
                            },
                            {
                                "color": "red",
                                "value": 5
                            }
                        ]
                    }
                }
            },
            "gridPos": {
                "h": 4,
                "w": 4,
                "x": 4,
                "y": 1
            },
            "id": 2,
            "options": {
                "reduceOptions": {
                    "calcs": [
                        "lastNotNull"
                    ]
                },
                "colorMode": "background",
                "graphMode": "area"
            },
            "title": "Error Rate (5xx)",
            "type": "stat",
            "targets": [
                {
                    "expr": "sum(rate(citl_http_errors_total{tenant=~\"$tenant\"}[1m]))",
                    "legendFormat": "err/s"
                }
            ]
        },
        {
            "datasource": {
                "type": "prometheus",
                "uid": "prometheus"
            },
            "fieldConfig": {
                "defaults": {
                    "unit": "ms",
                    "thresholds": {
                        "mode": "absolute",
                        "steps": [
                            {
                                "color": "green",
                                "value": null
                            },
                            {
                                "color": "yellow",
                                "value": 200
                            },
                            {
                                "color": "red",
                                "value": 1000
                            }
                        ]
                    }
                }
            },
            "gridPos": {
                "h": 4,
                "w": 4,
                "x": 8,
                "y": 1
            },
            "id": 3,
            "options": {
                "reduceOptions": {
                    "calcs": [
                        "lastNotNull"
                    ]
                },
                "colorMode": "background",
                "graphMode": "area"
            },
            "title": "Avg Latency",
            "type": "stat",
            "targets": [
                {
                    "expr": "sum(rate(citl_http_request_duration_milliseconds_sum{tenant=~\"$tenant\"}[1m])) / sum(rate(citl_http_request_duration_milliseconds_count{tenant=~\"$tenant\"}[1m]))",
                    "legendFormat": "ms"
                }
            ]
        },
        {
            "datasource": {
                "type": "prometheus",
                "uid": "prometheus"
            },
            "fieldConfig": {
                "defaults": {
                    "unit": "none",
                    "thresholds": {
                        "mode": "absolute",
                        "steps": [
                            {
                                "color": "blue",
                                "value": null
                            }
                        ]
                    }
                }
            },
            "gridPos": {
                "h": 4,
                "w": 4,
                "x": 12,
                "y": 1
            },
            "id": 4,
            "options": {
                "reduceOptions": {
                    "calcs": [
                        "lastNotNull"
                    ]
                },
                "colorMode": "background",
                "graphMode": "area"
            },
            "title": "Total Requests",
            "type": "stat",
            "targets": [
                {
                    "expr": "sum(citl_http_requests_total{tenant=~\"$tenant\"})",
                    "legendFormat": "total"
                }
            ]
        },
        {
            "datasource": {
                "type": "prometheus",
                "uid": "prometheus"
            },
            "fieldConfig": {
                "defaults": {
                    "unit": "none",
                    "thresholds": {
                        "mode": "absolute",
                        "steps": [
                            {
                                "color": "blue",
                                "value": null
                            }
                        ]
                    }
                }
            },
            "gridPos": {
                "h": 4,
                "w": 4,
                "x": 16,
                "y": 1
            },
            "id": 5,
            "options": {
                "reduceOptions": {
                    "calcs": [
                        "lastNotNull"
                    ]
                },
                "colorMode": "background",
                "graphMode": "area"
            },
            "title": "Active Connections",
            "type": "stat",
            "targets": [
                {
                    "expr": "sum(kestrel_active_connections)",
                    "legendFormat": "connections"
                }
            ]
        },
        {
            "datasource": {
                "type": "prometheus",
                "uid": "prometheus"
            },
            "fieldConfig": {
                "defaults": {
                    "unit": "percent",
                    "thresholds": {
                        "mode": "absolute",
                        "steps": [
                            {
                                "color": "green",
                                "value": null
                            },
                            {
                                "color": "yellow",
                                "value": 1
                            },
                            {
                                "color": "red",
                                "value": 5
                            }
                        ]
                    }
                }
            },
            "gridPos": {
                "h": 4,
                "w": 4,
                "x": 20,
                "y": 1
            },
            "id": 6,
            "options": {
                "reduceOptions": {
                    "calcs": [
                        "lastNotNull"
                    ]
                },
                "colorMode": "background",
                "graphMode": "area"
            },
            "title": "Error %",
            "type": "stat",
            "targets": [
                {
                    "expr": "sum(rate(citl_http_errors_total{tenant=~\"$tenant\"}[1m])) / sum(rate(citl_http_requests_total{tenant=~\"$tenant\"}[1m])) * 100",
                    "legendFormat": "%"
                }
            ]
        },
        {
            "collapsed": false,
            "gridPos": {
                "h": 1,
                "w": 24,
                "x": 0,
                "y": 5
            },
            "id": 200,
            "title": "🌐 HTTP Performance",
            "type": "row"
        },
        {
            "datasource": {
                "type": "prometheus",
                "uid": "prometheus"
            },
            "fieldConfig": {
                "defaults": {
                    "unit": "ms",
                    "custom": {
                        "drawStyle": "line",
                        "fillOpacity": 15,
                        "lineWidth": 2,
                        "pointSize": 5,
                        "showPoints": "auto"
                    }
                }
            },
            "gridPos": {
                "h": 8,
                "w": 12,
                "x": 0,
                "y": 6
            },
            "id": 7,
            "options": {
                "legend": {
                    "displayMode": "table",
                    "calcs": [
                        "mean",
                        "max",
                        "lastNotNull"
                    ]
                },
                "tooltip": {
                    "mode": "multi"
                }
            },
            "title": "Request Duration Percentiles",
            "type": "timeseries",
            "targets": [
                {
                    "expr": "histogram_quantile(0.50, sum(rate(citl_http_request_duration_milliseconds_bucket{tenant=~\"$tenant\"}[1m])) by (le))",
                    "legendFormat": "p50"
                },
                {
                    "expr": "histogram_quantile(0.90, sum(rate(citl_http_request_duration_milliseconds_bucket{tenant=~\"$tenant\"}[1m])) by (le))",
                    "legendFormat": "p90"
                },
                {
                    "expr": "histogram_quantile(0.95, sum(rate(citl_http_request_duration_milliseconds_bucket{tenant=~\"$tenant\"}[1m])) by (le))",
                    "legendFormat": "p95"
                },
                {
                    "expr": "histogram_quantile(0.99, sum(rate(citl_http_request_duration_milliseconds_bucket{tenant=~\"$tenant\"}[1m])) by (le))",
                    "legendFormat": "p99"
                }
            ]
        },
        {
            "datasource": {
                "type": "prometheus",
                "uid": "prometheus"
            },
            "fieldConfig": {
                "defaults": {
                    "unit": "reqps",
                    "custom": {
                        "drawStyle": "line",
                        "fillOpacity": 20,
                        "lineWidth": 2,
                        "stacking": {
                            "mode": "normal"
                        }
                    }
                }
            },
            "gridPos": {
                "h": 8,
                "w": 12,
                "x": 12,
                "y": 6
            },
            "id": 8,
            "options": {
                "legend": {
                    "displayMode": "table",
                    "calcs": [
                        "mean",
                        "lastNotNull"
                    ]
                },
                "tooltip": {
                    "mode": "multi"
                }
            },
            "title": "Request Rate by Status Code",
            "type": "timeseries",
            "targets": [
                {
                    "expr": "sum by (http_response_status_code) (rate(citl_http_requests_total{tenant=~\"$tenant\"}[1m]))",
                    "legendFormat": "{{http_response_status_code}}"
                }
            ]
        },
        {
            "datasource": {
                "type": "prometheus",
                "uid": "prometheus"
            },
            "fieldConfig": {
                "defaults": {
                    "unit": "reqps",
                    "custom": {
                        "drawStyle": "bars",
                        "fillOpacity": 80,
                        "lineWidth": 1,
                        "stacking": {
                            "mode": "normal"
                        }
                    }
                }
            },
            "gridPos": {
                "h": 8,
                "w": 12,
                "x": 0,
                "y": 14
            },
            "id": 9,
            "options": {
                "legend": {
                    "displayMode": "table",
                    "calcs": [
                        "mean",
                        "lastNotNull"
                    ]
                },
                "tooltip": {
                    "mode": "multi"
                }
            },
            "title": "Request Rate by Endpoint",
            "type": "timeseries",
            "targets": [
                {
                    "expr": "sum by (http_route) (rate(citl_http_requests_total{tenant=~\"$tenant\"}[1m]))",
                    "legendFormat": "{{http_route}}"
                }
            ]
        },
        {
            "datasource": {
                "type": "prometheus",
                "uid": "prometheus"
            },
            "fieldConfig": {
                "defaults": {
                    "unit": "reqps",
                    "custom": {
                        "drawStyle": "line",
                        "fillOpacity": 15,
                        "lineWidth": 2
                    }
                }
            },
            "gridPos": {
                "h": 8,
                "w": 12,
                "x": 12,
                "y": 14
            },
            "id": 10,
            "options": {
                "legend": {
                    "displayMode": "table",
                    "calcs": [
                        "mean",
                        "lastNotNull"
                    ]
                },
                "tooltip": {
                    "mode": "multi"
                }
            },
            "title": "Request Rate by Method",
            "type": "timeseries",
            "targets": [
                {
                    "expr": "sum by (http_request_method) (rate(citl_http_requests_total{tenant=~\"$tenant\"}[1m]))",
                    "legendFormat": "{{http_request_method}}"
                }
            ]
        },
        {
            "datasource": {
                "type": "prometheus",
                "uid": "prometheus"
            },
            "fieldConfig": {
                "defaults": {
                    "unit": "reqps",
                    "custom": {
                        "drawStyle": "line",
                        "fillOpacity": 15,
                        "lineWidth": 2,
                        "stacking": {
                            "mode": "normal"
                        }
                    }
                }
            },
            "gridPos": {
                "h": 8,
                "w": 12,
                "x": 0,
                "y": 22
            },
            "id": 11,
            "options": {
                "legend": {
                    "displayMode": "table",
                    "calcs": [
                        "mean",
                        "lastNotNull"
                    ]
                },
                "tooltip": {
                    "mode": "multi"
                }
            },
            "title": "Request Rate by Tenant",
            "type": "timeseries",
            "targets": [
                {
                    "expr": "sum by (tenant) (rate(citl_http_requests_total{tenant=~\"$tenant\"}[1m]))",
                    "legendFormat": "{{tenant}}"
                }
            ]
        },
        {
            "datasource": {
                "type": "prometheus",
                "uid": "prometheus"
            },
            "fieldConfig": {
                "defaults": {
                    "unit": "s",
                    "custom": {
                        "drawStyle": "line",
                        "fillOpacity": 15,
                        "lineWidth": 2
                    }
                }
            },
            "gridPos": {
                "h": 8,
                "w": 12,
                "x": 12,
                "y": 22
            },
            "id": 12,
            "options": {
                "legend": {
                    "displayMode": "table",
                    "calcs": [
                        "mean",
                        "max",
                        "lastNotNull"
                    ]
                },
                "tooltip": {
                    "mode": "multi"
                }
            },
            "title": "ASP.NET Core Request Duration (OTel)",
            "type": "timeseries",
            "targets": [
                {
                    "expr": "histogram_quantile(0.50, sum(rate(http_server_request_duration_seconds_bucket[1m])) by (le))",
                    "legendFormat": "p50"
                },
                {
                    "expr": "histogram_quantile(0.95, sum(rate(http_server_request_duration_seconds_bucket[1m])) by (le))",
                    "legendFormat": "p95"
                },
                {
                    "expr": "histogram_quantile(0.99, sum(rate(http_server_request_duration_seconds_bucket[1m])) by (le))",
                    "legendFormat": "p99"
                }
            ]
        },
        {
            "datasource": {
                "type": "prometheus",
                "uid": "prometheus"
            },
            "fieldConfig": {
                "defaults": {
                    "unit": "none",
                    "custom": {
                        "drawStyle": "line",
                        "fillOpacity": 15,
                        "lineWidth": 2
                    }
                }
            },
            "gridPos": {
                "h": 8,
                "w": 12,
                "x": 0,
                "y": 30
            },
            "id": 13,
            "options": {
                "legend": {
                    "displayMode": "table",
                    "calcs": [
                        "lastNotNull"
                    ]
                },
                "tooltip": {
                    "mode": "multi"
                }
            },
            "title": "ASP.NET Core Active Requests",
            "type": "timeseries",
            "targets": [
                {
                    "expr": "sum(http_server_active_requests)",
                    "legendFormat": "active"
                }
            ]
        },
        {
            "datasource": {
                "type": "prometheus",
                "uid": "prometheus"
            },
            "fieldConfig": {
                "defaults": {
                    "unit": "none",
                    "custom": {
                        "drawStyle": "line",
                        "fillOpacity": 15,
                        "lineWidth": 2
                    }
                }
            },
            "gridPos": {
                "h": 8,
                "w": 12,
                "x": 12,
                "y": 30
            },
            "id": 14,
            "options": {
                "legend": {
                    "displayMode": "table",
                    "calcs": [
                        "lastNotNull"
                    ]
                },
                "tooltip": {
                    "mode": "multi"
                }
            },
            "title": "Routing Match Attempts",
            "type": "timeseries",
            "targets": [
                {
                    "expr": "sum by (aspnetcore_routing_is_fallback) (rate(aspnetcore_routing_match_attempts_total[1m]))",
                    "legendFormat": "fallback={{aspnetcore_routing_is_fallback}}"
                }
            ]
        },
        {
            "collapsed": false,
            "gridPos": {
                "h": 1,
                "w": 24,
                "x": 0,
                "y": 38
            },
            "id": 300,
            "title": "⚙️ .NET Runtime",
            "type": "row"
        },
        {
            "datasource": {
                "type": "prometheus",
                "uid": "prometheus"
            },
            "fieldConfig": {
                "defaults": {
                    "unit": "percentunit",
                    "min": 0,
                    "max": 1,
                    "thresholds": {
                        "mode": "absolute",
                        "steps": [
                            {
                                "color": "green",
                                "value": null
                            },
                            {
                                "color": "yellow",
                                "value": 0.5
                            },
                            {
                                "color": "red",
                                "value": 0.8
                            }
                        ]
                    },
                    "custom": {
                        "drawStyle": "line",
                        "fillOpacity": 20,
                        "lineWidth": 2
                    }
                }
            },
            "gridPos": {
                "h": 8,
                "w": 8,
                "x": 0,
                "y": 39
            },
            "id": 15,
            "options": {
                "legend": {
                    "displayMode": "list"
                },
                "tooltip": {
                    "mode": "multi"
                }
            },
            "title": "CPU Usage (rate)",
            "type": "timeseries",
            "targets": [
                {
                    "expr": "rate(dotnet_process_cpu_time_seconds_total[1m])",
                    "legendFormat": "CPU cores used"
                }
            ]
        },
        {
            "datasource": {
                "type": "prometheus",
                "uid": "prometheus"
            },
            "fieldConfig": {
                "defaults": {
                    "unit": "bytes",
                    "custom": {
                        "drawStyle": "line",
                        "fillOpacity": 20,
                        "lineWidth": 2
                    }
                }
            },
            "gridPos": {
                "h": 8,
                "w": 8,
                "x": 8,
                "y": 39
            },
            "id": 16,
            "options": {
                "legend": {
                    "displayMode": "list"
                },
                "tooltip": {
                    "mode": "multi"
                }
            },
            "title": "Process Memory",
            "type": "timeseries",
            "targets": [
                {
                    "expr": "dotnet_process_memory_working_set_bytes",
                    "legendFormat": "working set"
                }
            ]
        },
        {
            "datasource": {
                "type": "prometheus",
                "uid": "prometheus"
            },
            "fieldConfig": {
                "defaults": {
                    "unit": "short",
                    "custom": {
                        "drawStyle": "line",
                        "fillOpacity": 15,
                        "lineWidth": 2
                    }
                }
            },
            "gridPos": {
                "h": 8,
                "w": 8,
                "x": 16,
                "y": 39
            },
            "id": 17,
            "options": {
                "legend": {
                    "displayMode": "table",
                    "calcs": [
                        "lastNotNull"
                    ]
                },
                "tooltip": {
                    "mode": "multi"
                }
            },
            "title": "GC Collections (rate/min)",
            "type": "timeseries",
            "targets": [
                {
                    "expr": "rate(dotnet_gc_collections_total[1m])",
                    "legendFormat": "gen {{dotnet_gc_heap_generation}}"
                }
            ]
        },
        {
            "datasource": {
                "type": "prometheus",
                "uid": "prometheus"
            },
            "fieldConfig": {
                "defaults": {
                    "unit": "bytes",
                    "custom": {
                        "drawStyle": "line",
                        "fillOpacity": 20,
                        "lineWidth": 2
                    }
                }
            },
            "gridPos": {
                "h": 8,
                "w": 8,
                "x": 0,
                "y": 47
            },
            "id": 18,
            "options": {
                "legend": {
                    "displayMode": "table",
                    "calcs": [
                        "lastNotNull"
                    ]
                },
                "tooltip": {
                    "mode": "multi"
                }
            },
            "title": "GC Heap Size by Generation",
            "type": "timeseries",
            "targets": [
                {
                    "expr": "dotnet_gc_last_collection_heap_size_bytes",
                    "legendFormat": "gen {{dotnet_gc_heap_generation}}"
                }
            ]
        },
        {
            "datasource": {
                "type": "prometheus",
                "uid": "prometheus"
            },
            "fieldConfig": {
                "defaults": {
                    "unit": "s",
                    "custom": {
                        "drawStyle": "line",
                        "fillOpacity": 15,
                        "lineWidth": 2
                    }
                }
            },
            "gridPos": {
                "h": 8,
                "w": 8,
                "x": 8,
                "y": 47
            },
            "id": 19,
            "options": {
                "legend": {
                    "displayMode": "list"
                },
                "tooltip": {
                    "mode": "multi"
                }
            },
            "title": "GC Pause Duration (rate)",
            "type": "timeseries",
            "targets": [
                {
                    "expr": "rate(dotnet_gc_pause_total_seconds[1m])",
                    "legendFormat": "pause sec/sec"
                }
            ]
        },
        {
            "datasource": {
                "type": "prometheus",
                "uid": "prometheus"
            },
            "fieldConfig": {
                "defaults": {
                    "unit": "short",
                    "custom": {
                        "drawStyle": "line",
                        "fillOpacity": 15,
                        "lineWidth": 2
                    }
                }
            },
            "gridPos": {
                "h": 8,
                "w": 8,
                "x": 16,
                "y": 47
            },
            "id": 20,
            "options": {
                "legend": {
                    "displayMode": "list"
                },
                "tooltip": {
                    "mode": "multi"
                }
            },
            "title": "Exceptions (rate)",
            "type": "timeseries",
            "targets": [
                {
                    "expr": "rate(dotnet_exceptions_total[1m])",
                    "legendFormat": "exceptions/sec"
                }
            ]
        },
        {
            "datasource": {
                "type": "prometheus",
                "uid": "prometheus"
            },
            "fieldConfig": {
                "defaults": {
                    "unit": "short",
                    "custom": {
                        "drawStyle": "line",
                        "fillOpacity": 15,
                        "lineWidth": 2
                    }
                }
            },
            "gridPos": {
                "h": 8,
                "w": 8,
                "x": 0,
                "y": 55
            },
            "id": 21,
            "options": {
                "legend": {
                    "displayMode": "table",
                    "calcs": [
                        "lastNotNull"
                    ]
                },
                "tooltip": {
                    "mode": "multi"
                }
            },
            "title": "Thread Pool Threads & Queue",
            "type": "timeseries",
            "targets": [
                {
                    "expr": "dotnet_thread_pool_thread_count",
                    "legendFormat": "active threads"
                },
                {
                    "expr": "dotnet_thread_pool_queue_length",
                    "legendFormat": "queue length"
                }
            ]
        },
        {
            "datasource": {
                "type": "prometheus",
                "uid": "prometheus"
            },
            "fieldConfig": {
                "defaults": {
                    "unit": "short",
                    "custom": {
                        "drawStyle": "line",
                        "fillOpacity": 15,
                        "lineWidth": 2
                    }
                }
            },
            "gridPos": {
                "h": 8,
                "w": 8,
                "x": 8,
                "y": 55
            },
            "id": 22,
            "options": {
                "legend": {
                    "displayMode": "list"
                },
                "tooltip": {
                    "mode": "multi"
                }
            },
            "title": "Thread Pool Work Items",
            "type": "timeseries",
            "targets": [
                {
                    "expr": "rate(dotnet_thread_pool_work_item_count_total[1m])",
                    "legendFormat": "work items/sec"
                },
                {
                    "expr": "rate(dotnet_thread_pool_completed_items_count_total[1m])",
                    "legendFormat": "completed/sec"
                }
            ]
        },
        {
            "datasource": {
                "type": "prometheus",
                "uid": "prometheus"
            },
            "fieldConfig": {
                "defaults": {
                    "unit": "short",
                    "custom": {
                        "drawStyle": "line",
                        "fillOpacity": 15,
                        "lineWidth": 2
                    }
                }
            },
            "gridPos": {
                "h": 8,
                "w": 8,
                "x": 16,
                "y": 55
            },
            "id": 23,
            "options": {
                "legend": {
                    "displayMode": "table",
                    "calcs": [
                        "lastNotNull"
                    ]
                },
                "tooltip": {
                    "mode": "multi"
                }
            },
            "title": "Lock Contention & Timers",
            "type": "timeseries",
            "targets": [
                {
                    "expr": "rate(dotnet_monitor_lock_contentions_total[1m])",
                    "legendFormat": "lock contentions/sec"
                },
                {
                    "expr": "dotnet_timer_count",
                    "legendFormat": "active timers"
                }
            ]
        },
        {
            "datasource": {
                "type": "prometheus",
                "uid": "prometheus"
            },
            "fieldConfig": {
                "defaults": {
                    "unit": "short"
                }
            },
            "gridPos": {
                "h": 4,
                "w": 4,
                "x": 0,
                "y": 63
            },
            "id": 24,
            "options": {
                "reduceOptions": {
                    "calcs": [
                        "lastNotNull"
                    ]
                },
                "colorMode": "value",
                "graphMode": "none"
            },
            "title": "Loaded Assemblies",
            "type": "stat",
            "targets": [
                {
                    "expr": "dotnet_assembly_count",
                    "legendFormat": "assemblies"
                }
            ]
        },
        {
            "datasource": {
                "type": "prometheus",
                "uid": "prometheus"
            },
            "fieldConfig": {
                "defaults": {
                    "unit": "decbytes"
                }
            },
            "gridPos": {
                "h": 4,
                "w": 4,
                "x": 4,
                "y": 63
            },
            "id": 25,
            "options": {
                "reduceOptions": {
                    "calcs": [
                        "lastNotNull"
                    ]
                },
                "colorMode": "value",
                "graphMode": "none"
            },
            "title": "JIT IL Bytes",
            "type": "stat",
            "targets": [
                {
                    "expr": "dotnet_jit_compiled_il_bytes_total",
                    "legendFormat": "IL bytes"
                }
            ]
        },
        {
            "datasource": {
                "type": "prometheus",
                "uid": "prometheus"
            },
            "fieldConfig": {
                "defaults": {
                    "unit": "short"
                }
            },
            "gridPos": {
                "h": 4,
                "w": 4,
                "x": 8,
                "y": 63
            },
            "id": 26,
            "options": {
                "reduceOptions": {
                    "calcs": [
                        "lastNotNull"
                    ]
                },
                "colorMode": "value",
                "graphMode": "none"
            },
            "title": "JIT Methods",
            "type": "stat",
            "targets": [
                {
                    "expr": "dotnet_jit_compiled_method_count_total",
                    "legendFormat": "methods"
                }
            ]
        },
        {
            "datasource": {
                "type": "prometheus",
                "uid": "prometheus"
            },
            "fieldConfig": {
                "defaults": {
                    "unit": "s"
                }
            },
            "gridPos": {
                "h": 4,
                "w": 4,
                "x": 12,
                "y": 63
            },
            "id": 55,
            "options": {
                "reduceOptions": {
                    "calcs": [
                        "lastNotNull"
                    ]
                },
                "colorMode": "value",
                "graphMode": "none"
            },
            "title": "JIT Compilation Time",
            "type": "stat",
            "targets": [
                {
                    "expr": "dotnet_jit_compilation_time_seconds_total",
                    "legendFormat": "seconds"
                }
            ]
        },
        {
            "datasource": {
                "type": "prometheus",
                "uid": "prometheus"
            },
            "fieldConfig": {
                "defaults": {
                    "unit": "bytes",
                    "custom": {
                        "drawStyle": "line",
                        "fillOpacity": 20,
                        "lineWidth": 2
                    }
                }
            },
            "gridPos": {
                "h": 8,
                "w": 8,
                "x": 16,
                "y": 63
            },
            "id": 56,
            "options": {
                "legend": {
                    "displayMode": "table",
                    "calcs": [
                        "lastNotNull"
                    ]
                },
                "tooltip": {
                    "mode": "multi"
                }
            },
            "title": "Heap Allocated Total (rate)",
            "type": "timeseries",
            "targets": [
                {
                    "expr": "rate(dotnet_gc_heap_total_allocated_bytes_total[1m])",
                    "legendFormat": "alloc bytes/sec"
                }
            ]
        },
        {
            "collapsed": false,
            "gridPos": {
                "h": 1,
                "w": 24,
                "x": 0,
                "y": 71
            },
            "id": 400,
            "title": "🔌 Kestrel & Connections",
            "type": "row"
        },
        {
            "datasource": {
                "type": "prometheus",
                "uid": "prometheus"
            },
            "fieldConfig": {
                "defaults": {
                    "unit": "short",
                    "custom": {
                        "drawStyle": "line",
                        "fillOpacity": 20,
                        "lineWidth": 2
                    }
                }
            },
            "gridPos": {
                "h": 8,
                "w": 8,
                "x": 0,
                "y": 72
            },
            "id": 27,
            "options": {
                "legend": {
                    "displayMode": "table",
                    "calcs": [
                        "lastNotNull",
                        "max"
                    ]
                },
                "tooltip": {
                    "mode": "multi"
                }
            },
            "title": "Kestrel Active Connections",
            "type": "timeseries",
            "targets": [
                {
                    "expr": "sum(kestrel_active_connections)",
                    "legendFormat": "active"
                }
            ]
        },
        {
            "datasource": {
                "type": "prometheus",
                "uid": "prometheus"
            },
            "fieldConfig": {
                "defaults": {
                    "unit": "s",
                    "custom": {
                        "drawStyle": "line",
                        "fillOpacity": 15,
                        "lineWidth": 2
                    }
                }
            },
            "gridPos": {
                "h": 8,
                "w": 8,
                "x": 8,
                "y": 72
            },
            "id": 28,
            "options": {
                "legend": {
                    "displayMode": "table",
                    "calcs": [
                        "mean",
                        "max",
                        "lastNotNull"
                    ]
                },
                "tooltip": {
                    "mode": "multi"
                }
            },
            "title": "Kestrel Connection Duration",
            "type": "timeseries",
            "targets": [
                {
                    "expr": "histogram_quantile(0.50, sum(rate(kestrel_connection_duration_seconds_bucket[1m])) by (le))",
                    "legendFormat": "p50"
                },
                {
                    "expr": "histogram_quantile(0.95, sum(rate(kestrel_connection_duration_seconds_bucket[1m])) by (le))",
                    "legendFormat": "p95"
                },
                {
                    "expr": "histogram_quantile(0.99, sum(rate(kestrel_connection_duration_seconds_bucket[1m])) by (le))",
                    "legendFormat": "p99"
                }
            ]
        },
        {
            "datasource": {
                "type": "prometheus",
                "uid": "prometheus"
            },
            "fieldConfig": {
                "defaults": {
                    "unit": "short",
                    "custom": {
                        "drawStyle": "line",
                        "fillOpacity": 15,
                        "lineWidth": 2
                    }
                }
            },
            "gridPos": {
                "h": 8,
                "w": 8,
                "x": 16,
                "y": 72
            },
            "id": 29,
            "options": {
                "legend": {
                    "displayMode": "table",
                    "calcs": [
                        "lastNotNull"
                    ]
                },
                "tooltip": {
                    "mode": "multi"
                }
            },
            "title": "Kestrel Queued Requests & Connections",
            "type": "timeseries",
            "targets": [
                {
                    "expr": "sum(kestrel_queued_requests)",
                    "legendFormat": "queued requests"
                },
                {
                    "expr": "sum(kestrel_queued_connections)",
                    "legendFormat": "queued connections"
                }
            ]
        },
        {
            "datasource": {
                "type": "prometheus",
                "uid": "prometheus"
            },
            "fieldConfig": {
                "defaults": {
                    "unit": "short",
                    "custom": {
                        "drawStyle": "line",
                        "fillOpacity": 15,
                        "lineWidth": 2
                    }
                }
            },
            "gridPos": {
                "h": 8,
                "w": 8,
                "x": 0,
                "y": 80
            },
            "id": 30,
            "options": {
                "legend": {
                    "displayMode": "table",
                    "calcs": [
                        "lastNotNull"
                    ]
                },
                "tooltip": {
                    "mode": "multi"
                }
            },
            "title": "Kestrel TLS Handshakes",
            "type": "timeseries",
            "targets": [
                {
                    "expr": "sum(kestrel_active_tls_handshakes)",
                    "legendFormat": "active TLS"
                },
                {
                    "expr": "rate(kestrel_tls_handshake_duration_seconds_count[1m])",
                    "legendFormat": "handshakes/sec"
                }
            ]
        },
        {
            "datasource": {
                "type": "prometheus",
                "uid": "prometheus"
            },
            "fieldConfig": {
                "defaults": {
                    "unit": "s",
                    "custom": {
                        "drawStyle": "line",
                        "fillOpacity": 15,
                        "lineWidth": 2
                    }
                }
            },
            "gridPos": {
                "h": 8,
                "w": 8,
                "x": 8,
                "y": 80
            },
            "id": 31,
            "options": {
                "legend": {
                    "displayMode": "list"
                },
                "tooltip": {
                    "mode": "multi"
                }
            },
            "title": "DNS Lookup Duration",
            "type": "timeseries",
            "targets": [
                {
                    "expr": "histogram_quantile(0.50, sum(rate(dns_lookup_duration_seconds_bucket[1m])) by (le))",
                    "legendFormat": "p50"
                },
                {
                    "expr": "histogram_quantile(0.95, sum(rate(dns_lookup_duration_seconds_bucket[1m])) by (le))",
                    "legendFormat": "p95"
                }
            ]
        },
        {
            "datasource": {
                "type": "prometheus",
                "uid": "prometheus"
            },
            "fieldConfig": {
                "defaults": {
                    "unit": "short",
                    "custom": {
                        "drawStyle": "line",
                        "fillOpacity": 15,
                        "lineWidth": 2
                    }
                }
            },
            "gridPos": {
                "h": 8,
                "w": 8,
                "x": 16,
                "y": 80
            },
            "id": 32,
            "options": {
                "legend": {
                    "displayMode": "table",
                    "calcs": [
                        "lastNotNull"
                    ]
                },
                "tooltip": {
                    "mode": "multi"
                }
            },
            "title": "HTTP Client Requests",
            "type": "timeseries",
            "targets": [
                {
                    "expr": "sum(http_client_active_requests)",
                    "legendFormat": "active"
                },
                {
                    "expr": "rate(http_client_request_duration_seconds_count[1m])",
                    "legendFormat": "req/sec"
                }
            ]
        },
        {
            "collapsed": false,
            "gridPos": {
                "h": 1,
                "w": 24,
                "x": 0,
                "y": 88
            },
            "id": 500,
            "title": "💾 Database Quick View",
            "type": "row"
        },
        {
            "datasource": {
                "type": "prometheus",
                "uid": "prometheus"
            },
            "fieldConfig": {
                "defaults": {
                    "unit": "ops",
                    "custom": {
                        "drawStyle": "line",
                        "fillOpacity": 20,
                        "lineWidth": 2
                    }
                }
            },
            "gridPos": {
                "h": 8,
                "w": 8,
                "x": 0,
                "y": 89
            },
            "id": 33,
            "options": {
                "legend": {
                    "displayMode": "table",
                    "calcs": [
                        "mean",
                        "lastNotNull"
                    ]
                },
                "tooltip": {
                    "mode": "multi"
                }
            },
            "title": "DB Query Rate by Tenant",
            "type": "timeseries",
            "targets": [
                {
                    "expr": "sum by (tenant) (rate(citl_db_queries_total{tenant=~\"$tenant\"}[1m]))",
                    "legendFormat": "{{tenant}}"
                }
            ]
        },
        {
            "datasource": {
                "type": "prometheus",
                "uid": "prometheus"
            },
            "fieldConfig": {
                "defaults": {
                    "unit": "ms",
                    "custom": {
                        "drawStyle": "line",
                        "fillOpacity": 15,
                        "lineWidth": 2
                    }
                }
            },
            "gridPos": {
                "h": 8,
                "w": 8,
                "x": 8,
                "y": 89
            },
            "id": 34,
            "options": {
                "legend": {
                    "displayMode": "table",
                    "calcs": [
                        "mean",
                        "max",
                        "lastNotNull"
                    ]
                },
                "tooltip": {
                    "mode": "multi"
                }
            },
            "title": "DB Query Duration Percentiles",
            "type": "timeseries",
            "targets": [
                {
                    "expr": "histogram_quantile(0.50, sum(rate(citl_db_query_duration_milliseconds_bucket{tenant=~\"$tenant\"}[1m])) by (le))",
                    "legendFormat": "p50"
                },
                {
                    "expr": "histogram_quantile(0.95, sum(rate(citl_db_query_duration_milliseconds_bucket{tenant=~\"$tenant\"}[1m])) by (le))",
                    "legendFormat": "p95"
                },
                {
                    "expr": "histogram_quantile(0.99, sum(rate(citl_db_query_duration_milliseconds_bucket{tenant=~\"$tenant\"}[1m])) by (le))",
                    "legendFormat": "p99"
                }
            ]
        },
        {
            "datasource": {
                "type": "prometheus",
                "uid": "prometheus"
            },
            "fieldConfig": {
                "defaults": {
                    "unit": "ops",
                    "custom": {
                        "drawStyle": "bars",
                        "fillOpacity": 80,
                        "lineWidth": 1,
                        "stacking": {
                            "mode": "normal"
                        }
                    }
                }
            },
            "gridPos": {
                "h": 8,
                "w": 8,
                "x": 16,
                "y": 89
            },
            "id": 35,
            "options": {
                "legend": {
                    "displayMode": "table",
                    "calcs": [
                        "mean",
                        "lastNotNull"
                    ]
                },
                "tooltip": {
                    "mode": "multi"
                }
            },
            "title": "DB Query Rate by Operation",
            "type": "timeseries",
            "targets": [
                {
                    "expr": "sum by (db_operation) (rate(citl_db_queries_total{tenant=~\"$tenant\"}[1m]))",
                    "legendFormat": "{{db_operation}}"
                }
            ]
        },
        {
            "collapsed": false,
            "gridPos": {
                "h": 1,
                "w": 24,
                "x": 0,
                "y": 97
            },
            "id": 600,
            "title": "📝 Logs",
            "type": "row"
        },
        {
            "datasource": {
                "type": "loki",
                "uid": "loki"
            },
            "gridPos": {
                "h": 10,
                "w": 24,
                "x": 0,
                "y": 98
            },
            "id": 36,
            "options": {
                "showTime": true,
                "showLabels": true,
                "showCommonLabels": false,
                "wrapLogMessage": true,
                "prettifyLogMessage": false,
                "enableLogDetails": true,
                "sortOrder": "Descending",
                "dedupStrategy": "none"
            },
            "title": "Error & Warning Logs",
            "type": "logs",
            "targets": [
                {
                    "expr": "{service_name=\"CITL.WebApi\"} |~ \"(?i)(error|warn|exception|fail)\" | json | __error__=\"\"",
                    "refId": "A"
                }
            ]
        },
        {
            "datasource": {
                "type": "loki",
                "uid": "loki"
            },
            "gridPos": {
                "h": 10,
                "w": 24,
                "x": 0,
                "y": 108
            },
            "id": 37,
            "options": {
                "showTime": true,
                "showLabels": true,
                "showCommonLabels": false,
                "wrapLogMessage": true,
                "prettifyLogMessage": false,
                "enableLogDetails": true,
                "sortOrder": "Descending",
                "dedupStrategy": "none"
            },
            "title": "All Application Logs",
            "type": "logs",
            "targets": [
                {
                    "expr": "{service_name=\"CITL.WebApi\"} | json | __error__=\"\"",
                    "refId": "A"
                }
            ]
        }
    ]
}
